bootstrap_grid_builder/__init__.py
bootstrap_grid_builder/abstract_models.py
bootstrap_grid_builder/apps.py
bootstrap_grid_builder/cms_plugins.py
bootstrap_grid_builder/fields.py
bootstrap_grid_builder/forms.py
bootstrap_grid_builder/models.py
bootstrap_grid_builder/receivers.py
bootstrap_grid_builder/settings.py
bootstrap_grid_builder/urls.py
bootstrap_grid_builder/utils.py
bootstrap_grid_builder/views.py
bootstrap_grid_builder/cms_wizards/__init__.py
bootstrap_grid_builder/cms_wizards/cms_wizards.py
bootstrap_grid_builder/cms_wizards/forms.py
bootstrap_grid_builder/cms_wizards/templates/cms/wizards/base.html
bootstrap_grid_builder/cms_wizards/templates/cms/wizards/create.html
bootstrap_grid_builder/cms_wizards/templates/cms/wizards/done.html
bootstrap_grid_builder/cms_wizards/templates/cms/wizards/start.html
bootstrap_grid_builder/cms_wizards/templates/cms/wizards/wizardoptionwidget.html
bootstrap_grid_builder/cms_wizards/templates/cms/wizards/includes/form_fields.html
bootstrap_grid_builder/migrations/0001_initial.py
bootstrap_grid_builder/migrations/0002_rename_cols_gridcolpluginmodel_cols_xs.py
bootstrap_grid_builder/migrations/0003_rename_variant_gridrowpluginmodel_variant_class.py
bootstrap_grid_builder/migrations/0004_auto_20210928_1115.py
bootstrap_grid_builder/migrations/0005_alter_gridcontainerpluginmodel_tag_type.py
bootstrap_grid_builder/migrations/__init__.py
bootstrap_grid_builder/static/cms_plugin_structure/page.css
bootstrap_grid_builder/static/cms_plugin_structure/page.js
bootstrap_grid_builder/static/cms_plugin_structure/dist/index.html
bootstrap_grid_builder/static/cms_plugin_structure/dist/js/app.js
bootstrap_grid_builder/templates/cms_plugin_structure/widgets/grid_builder.html
bootstrap_grid_builder/templates/configurable_grid/configurable_grid.html
bootstrap_grid_builder/templates/configurable_grid/grid_column.html
bootstrap_grid_builder/templates/configurable_grid/grid_container.html
django_cms_bootstrap_grid_builder-0.1.2.dist-info/LICENSE.md
django_cms_bootstrap_grid_builder-0.1.2.dist-info/METADATA
django_cms_bootstrap_grid_builder-0.1.2.dist-info/WHEEL
django_cms_bootstrap_grid_builder-0.1.2.dist-info/top_level.txt
django_cms_bootstrap_grid_builder-0.1.2.dist-info/RECORD
