Metadata-Version: 2.1
Name: django-cms-bootstrap-grid-builder
Version: 0.1.2
Summary: Your project description goes here
Home-page: https://github.com/frankhood/django-cms-bootstrap-grid-builder
Author: FrankHood Business Solutions srl
Author-email: info@frankhood.it
License: MIT
Keywords: django-cms-bootstrap-grid-builder
Platform: UNKNOWN
Classifier: Development Status :: 3 - Alpha
Classifier: Framework :: Django :: 2.2
Classifier: Framework :: Django :: 3.2
Classifier: Intended Audience :: Developers
Classifier: License :: OSI Approved :: BSD License
Classifier: Natural Language :: English
Classifier: Programming Language :: Python :: 3.6
Classifier: Programming Language :: Python :: 3.7
Classifier: Programming Language :: Python :: 3.8
Classifier: Programming Language :: Python :: 3.9
License-File: LICENSE.md
Requires-Dist: Django (>=2.2)
Requires-Dist: django-cms (>=3.7.0)
Requires-Dist: jsonfield (>=2.0.2)
Requires-Dist: django-jsoneditor (>=0.1.6)
